custom_dataframe/__init__.py
custom_dataframe/frontend/build/asset-manifest.json
custom_dataframe/frontend/build/bootstrap.min.css
custom_dataframe/frontend/build/index.html
custom_dataframe/frontend/build/static/css/main.7ab9fd41.css
custom_dataframe/frontend/build/static/css/main.7ab9fd41.css.map
custom_dataframe/frontend/build/static/css/main.f2ff7324.css
custom_dataframe/frontend/build/static/css/main.f2ff7324.css.map
custom_dataframe/frontend/build/static/js/main.8b57b089.js
custom_dataframe/frontend/build/static/js/main.8b57b089.js.LICENSE.txt
custom_dataframe/frontend/build/static/js/main.8b57b089.js.map
custom_dataframe/frontend/build/static/js/main.a41cdd7e.js
custom_dataframe/frontend/build/static/js/main.a41cdd7e.js.LICENSE.txt
custom_dataframe/frontend/build/static/js/main.a41cdd7e.js.map
streamlit_custom_dataframe_test-0.0.2.dist-info/LICENSE
streamlit_custom_dataframe_test-0.0.2.dist-info/METADATA
streamlit_custom_dataframe_test-0.0.2.dist-info/WHEEL
streamlit_custom_dataframe_test-0.0.2.dist-info/top_level.txt
streamlit_custom_dataframe_test-0.0.2.dist-info/RECORD
